nets/__init__.py
nets/cuda.py
nets/numeric.py
nets/tensor.py
nets/autograd/__init__.py
nets/autograd/_utils.py
nets/autograd/function.py
nets/autograd/functional.py
nets/autograd/functions.py
nets/autograd/hook.py
nets/autograd/numeric.py
nets/autograd/operation.py
nets/autograd/ops.py
nets/autograd/parameter.py
nets/autograd/utils.py
nets/data/__init__.py
nets/data/_utils.py
nets/data/batch.py
nets/data/dataset.py
nets/data/example.py
nets/data/iterator.py
nets/datasets/__init__.py
nets/datasets/cifar.py
nets/datasets/mnist.py
nets/datasets/svhn.py
nets/nn/__init__.py
nets/nn/activation.py
nets/nn/functional.py
nets/nn/loss.py
nets/nn/utils.py
nets/nn/modules/__init__.py
nets/nn/modules/_utils.py
nets/nn/modules/conv.py
nets/nn/modules/dnn.py
nets/nn/modules/dropout.py
nets/nn/modules/linear.py
nets/nn/modules/module.py
nets/nn/modules/pool.py
nets/nn/modules/rnn.py
nets/nn/modules/rnnbase.py
nets/nn/modules/sequential.py
nets/optim/__init__.py
nets/optim/adagrad.py
nets/optim/adam.py
nets/optim/optimizer.py
nets/optim/rmsprop.py
nets/optim/sgd.py
nets/solver/__init__.py
nets/solver/solver.py
nets/utils/__init__.py
nets/utils/decorator.py
nets/utils/display.py
nets/utils/errors.py
nets/utils/functions.py
vanilla/__init__.py
vanilla/cnn.py
vanilla/dnn.py
vanilla/rnn.py
nets-0.0.3.1.dist-info/LICENSE
nets-0.0.3.1.dist-info/METADATA
nets-0.0.3.1.dist-info/WHEEL
nets-0.0.3.1.dist-info/top_level.txt
nets-0.0.3.1.dist-info/RECORD
