Metadata-Version: 2.1
Name: nets
Version: 0.0.3.1
Summary: Neural Network with NumPy.
Home-page: https://github.com/arthurdjn/nets
Author: Arthur Dujardin
Author-email: arthur.dujardin@ensg.eu
License: Apache License-2.0
Platform: UNKNOWN
Classifier: Development Status :: 5 - Production/Stable
Classifier: Intended Audience :: Developers
Classifier: Topic :: Software Development :: Build Tools
Classifier: Programming Language :: Python :: 3
Requires-Dist: numpy
